aima3/__init__.py
aima3/agents.py
aima3/csp.py
aima3/games.py
aima3/ipyviews.py
aima3/knowledge.py
aima3/learning.py
aima3/logic.py
aima3/mcts.py
aima3/mdp.py
aima3/nlp.py
aima3/notebook.py
aima3/planning.py
aima3/probability.py
aima3/rl.py
aima3/search.py
aima3/text.py
aima3/tictactoe.py
aima3/utils.py
aima3/tests/__init__.py
aima3/tests/test_agents.py
aima3/tests/test_csp.py
aima3/tests/test_games.py
aima3/tests/test_knowledge.py
aima3/tests/test_learning.py
aima3/tests/test_logic.py
aima3/tests/test_mdp.py
aima3/tests/test_nlp.py
aima3/tests/test_planning.py
aima3/tests/test_probability.py
aima3/tests/test_rl.py
aima3/tests/test_search.py
aima3/tests/test_text.py
aima3/tests/test_utils.py
aima3-1.0.11.dist-info/METADATA
aima3-1.0.11.dist-info/RECORD
aima3-1.0.11.dist-info/WHEEL
aima3-1.0.11.dist-info/top_level.txt
