Metadata-Version: 1.1
Name: aima3
Version: 1.0.11
Summary: Artificial Intelligence: A Modern Approach, in Python3
Home-page: https://github.com/Calysto/aima3
Author: Douglas Blank
Author-email: doug.blank@gmail.com
License: UNKNOWN
Platform: UNKNOWN
Classifier: Framework :: IPython
Classifier: License :: OSI Approved :: BSD License
Classifier: Programming Language :: Python :: 3
